envname.py
envname-1.0.5.2.dist-info/entry_points.txt
envname-1.0.5.2.dist-info/LICENSE
envname-1.0.5.2.dist-info/WHEEL
envname-1.0.5.2.dist-info/METADATA
envname-1.0.5.2.dist-info/RECORD
