Metadata-Version: 2.1
Name: envname
Version: 1.0.5.2
Summary: 为运行环境设置名称
Author-email: "lcctoor.com" <lcctoor@outlook.com>
Classifier: License :: OSI Approved :: Apache Software License
Requires-Dist: arts>=2023.11.26
Project-URL: HomePage, https://github.com/lcctoor/arts/tree/main/arts
